eelgraph/__init__.py
eelgraph/charts.py
eelgraph/colors.py
eelgraph/ui/chart.html
eelgraph/ui/css/loadfonts.css
eelgraph/ui/css/style.css
eelgraph/ui/fonts/rubik-v7-latin-regular.eot
eelgraph/ui/fonts/rubik-v7-latin-regular.svg
eelgraph/ui/fonts/rubik-v7-latin-regular.ttf
eelgraph/ui/fonts/rubik-v7-latin-regular.woff
eelgraph/ui/fonts/rubik-v7-latin-regular.woff2
eelgraph/ui/js/Chart.bundle.min.js
eelgraph/ui/js/loadchart.js
eelgraph-0.0.2.dist-info/LICENSE
eelgraph-0.0.2.dist-info/METADATA
eelgraph-0.0.2.dist-info/WHEEL
eelgraph-0.0.2.dist-info/top_level.txt
eelgraph-0.0.2.dist-info/RECORD
