Metadata-Version: 2.1
Name: eelgraph
Version: 0.0.2
Summary: creates live chart.js charts from python
Home-page: https://github.com/jamsterwes/eelgraph
Author: Wes Taylor
Author-email: jamsterwes@gmail.com
License: UNKNOWN
Platform: UNKNOWN
Classifier: Programming Language :: Python :: 3
Classifier: License :: OSI Approved :: MIT License
Classifier: Operating System :: OS Independent
